mongomini/__init__.py
mongomini-23.3.0.dist-info/METADATA
mongomini-23.3.0.dist-info/WHEEL
mongomini-23.3.0.dist-info/licenses/LICENSE
mongomini-23.3.0.dist-info/RECORD
